setup.py
of/README.md
of/__init__.py
of/dev-requirements.txt
of/requirements.txt
of.egg-info/PKG-INFO
of.egg-info/SOURCES.txt
of.egg-info/dependency_links.txt
of.egg-info/requires.txt
of.egg-info/top_level.txt
of/broker/README.md
of/broker/__init__.py
of/broker/broker.py
of/broker/brokersrvc.py
of/broker/globals.py
of/broker/cherrypy_api/README.md
of/broker/cherrypy_api/__init__.py
of/broker/cherrypy_api/authentication.py
of/broker/cherrypy_api/broker.py
of/broker/cherrypy_api/node.py
of/broker/examples/README.md
of/broker/examples/__init__.py
of/broker/examples/partial/README.md
of/broker/examples/partial/__init__.py
of/broker/examples/partial/cherrypy_server.py
of/broker/lib/README.md
of/broker/lib/__init__.py
of/broker/lib/access.py
of/broker/lib/auth_backend.py
of/broker/lib/logging.py
of/broker/lib/node.py
of/broker/lib/schema_mongodb.py
of/broker/lib/messaging/__init__.py
of/broker/lib/messaging/handler.py
of/broker/lib/messaging/websocket.py
of/broker/testing/README.md
of/broker/testing/__init__.py
of/broker/testing/data_struct.json
of/broker/testing/init.json
of/broker/testing/init.py
of/broker/testing/init_env.py
of/broker/ui/README.md
of/broker/ui/index.html
of/common/README.md
of/common/__init__.py
of/common/aspect_utilities.py
of/common/cumulative_dict.py
of/common/dictionaries.py
of/common/internal.py
of/common/logging.py
of/common/plugins.py
of/common/settings.py
of/common/messaging/__init__.py
of/common/messaging/constants.py
of/common/messaging/factory.py
of/common/messaging/handler.py
of/common/messaging/utils.py
of/common/messaging/websocket.py
of/common/queue/__init__.py
of/common/queue/handler.py
of/common/queue/monitor.py
of/common/security/__init__.py
of/common/security/authentication.py
of/common/security/groups.py
of/common/security/permission.py
of/forms/README.md
of/forms/__init__.py
of/forms/node.forms.json
of/forms/namespaces/of/node/admin/default.json
of/forms/namespaces/of/node/broker/default.json
of/forms/namespaces/of/node/group/default.json
of/forms/namespaces/of/node/node/default.json
of/forms/namespaces/of/node/right/default.json
