Metadata-Version: 1.0
Name: of
Version: 0.14.7
Summary: The Optimal Framework is the fastest path to building any modern multi-user system
Home-page: https://github.com/OptimalBPM/of
Author: Nicklas Boerjesson
Author-email: nicklas_attheold_optimalbpm.se
License: BSD
Platform: UNKNOWN
